setup.py
ProbabilityDistributionsHLO/Binomialdistribution.py
ProbabilityDistributionsHLO/Gaussiandistribution.py
ProbabilityDistributionsHLO/Generaldistribution.py
ProbabilityDistributionsHLO/__init__.py
ProbabilityDistributionsHLO.egg-info/PKG-INFO
ProbabilityDistributionsHLO.egg-info/SOURCES.txt
ProbabilityDistributionsHLO.egg-info/dependency_links.txt
ProbabilityDistributionsHLO.egg-info/not-zip-safe
ProbabilityDistributionsHLO.egg-info/top_level.txt